LICENSE
MANIFEST.in
README.md
setup.py
python_xtea3.egg-info/PKG-INFO
python_xtea3.egg-info/SOURCES.txt
python_xtea3.egg-info/dependency_links.txt
python_xtea3.egg-info/top_level.txt
xtea3/__init__.py
xtea3/tests.py
xtea3/xtea3.c
xtea3/xtea3.cpython-312-x86_64-linux-gnu.so
xtea3/xtea3.pyx