Metadata-Version: 2.4
Name: python-xtea3
Version: 0.2.0
Summary: XTEA3 implementation
Home-page: https://github.com/pikhovkin/python-xtea3
Author: Sergei Pikhovkin
License: MIT
Keywords: xtea3
Classifier: Development Status :: 5 - Production/Stable
Classifier: Intended Audience :: Developers
Classifier: Programming Language :: Python :: 3.12
Classifier: Programming Language :: Python :: 3.13
Classifier: Programming Language :: Python :: 3.14
Classifier: Programming Language :: Python :: 3.15
Requires-Python: >=3.12,<4.0
License-File: LICENSE
Dynamic: author
Dynamic: classifier
Dynamic: description
Dynamic: description-content-type
Dynamic: home-page
Dynamic: keywords
Dynamic: license
Dynamic: license-file
Dynamic: requires-python
Dynamic: summary
